{"履修期": "春学期集中", "主な教授言語": "日本語", "授業目的": "本授業の目的は、学生がフィールドワークを通じて韓国の文化を学ぶことである。<BR/>また、英語でのポスター発表を実施する能力を身に付けることも目的としている。", "到達目標": "学生はフィールドワークを通じて、韓国の文化を学ぶことができる。<BR/>また、英語でポスター発表を実施することができる。", "特記事項": "", "関連科目": "", "授業の概要・背景": "韓国の首都ソウルに4日間滞在して学びを深める。その間、高麗大学世宗キャンパスを訪問し、ポスター発表会（英語）を実施する。授業は、事前授業、韓国でのポスター発表、フィールド調査、事後レポートの提出という構成である。参加者は韓国の歴史・社会・文化などのテーマについて主体的に調べて準備を行い、ソウルでの調査を通じて、それぞれのテーマについての理解を深める。", "授業方法": "事前講義、ポスター制作、ポスター発表、フィールドワーク、事後レポート提出", "トピック": {"第1回": ["4/10（月）オリエンテーション、ポスター発表会準備", "ポスター発表の内容を考える"], "第2回": ["4/17（月）フィールドワーク事前調査", "フィールドワークの内容を調査する"], "第3回": ["5/8（月）ポスター発表会準備", "ポスター発表のための準備（ポスターを完成させる）"], "第4回": ["5/15（月）ポスター発表会準備", "ポスター発表のための準備（ポスターを印刷する）"], "第5回": ["5/19（金）午後　フィールドワーク調査（ソウル市内、イテウォン地区など）", "特に無し"], "第6回": ["5/19（金）午後　フィールドワーク調査（ソウル市内、ソウル市立美術館など）", "特に無し"], "第7回": ["5/19（金）午後　フィールドワーク調査・報告（ソウル市内、景福宮など）", "当日の振り返りと翌日の準備"], "第8回": ["5/20（土）午前　高麗大学セジョン校にて　ポスター発表会", "特に無し"], "第9回": ["5/20（土）午前　高麗大学セジョン校にて　ポスター発表会", "特に無し"], "第10回": ["5/20（土）午後　高麗大学セジョン校主催によるエクスカーション", "特に無し"], "第11回": ["5/20（土）午後　高麗大学セジョン校にて　学生との交流会", "当日の振り返りと翌日の準備"], "第12回": ["5/21（日）午前　フィールドワーク調査（水原）", "特に無し"], "第13回": ["5/21（日）午後　フィールドワーク調査（水原）", "特に無し"], "第14回": ["5/21（日）午後　フィールドワーク調査・報告（ソウル市内）", "当日の振り返りと翌日の準備"], "第15回": ["5/22（月）午前　フィールドワーク調査・報告（ソウル市内）", "事後レポートの作成"]}, "評価": {"成績評価Grading0": ["種別　Type備考　Note", "割合　Percentage", "評価基準等　Grading Criteria etc."], "成績評価Grading1": ["その他／Others (99)", "100 %", "ポスター制作、ポスター発表、フィールドワーク、事後レポート（2000字）"], "備考Note0": "本授業は、学期中に実施される韓国でのフィールドワークが主な授業内容である。\nフィールドワーク実施期間は5月19日（金）から22日（月）の予定である。\n当該期間（金曜日および月曜日）に実施される他の講義・演習等の科目を欠席しなければならないことを了承の上、履修すること。", "更新日時/Date of Update1": "2023年04月27日 22時26分39秒", "項番No.0": [], "項番No.1": ["2023年度", "春学期集中／Intensive (Spring)", "集中・その他／Concentration/Other", "春学期集中／Intensive (Spring)", "未定"]}, "campas": 0, "name": "【200】人文学総合２６／Comprehensive Studies 26", "管理部署": 1, "単位数": 2, "担当者": "小石　かつら（KOISHI KATSURA） ", "履修基準年度": "２年", "緊急授業形態": 0, "オンライン授業形態": 4, "時限1": 49, "評価1": 4, "開講期": 8}