{"履修期": "春学期", "主な教授言語": "日本語", "授業目的": "　私自身を含めて人びとは、たくさんの「あたりまえ」にとらわれて生きています。「そういうものだから」「それがあたりまえだから」と思いながら、とくに疑問に感じることもなく、毎日たくさんのことをやり過ごしています。 <br />　本演習の目的は、現代社会の様々な局面を分析するために必要な、「あたりまえ（常識）」にとらわれない社会学的な「ものの見方」を身につけることにあります。したがって本演習で検討される様々な社会学理論は、理論のための理論ではなく、あなた自身が現在（いま）を考え生きるための「パースペクティブ（ものの見方）」として取り扱われることになるでしょう。 <br />　本演習を通じて、あなた自身を、あなたをとりまく人びとを、そしてあなたがいるこの時代を、「あたりまえ」だと終わらせてしまうことなく大切に丁寧に語る、自分だけの言葉を探す旅の一歩をふみだしてほしいと願っています。", "到達目標": "１）日常生活の「あたりまえ（常識）」を見直してみる。 <br />２）社会と自分がどのように関係しているのかを考える。 <br />３）以上のことを考えるために社会学的な対象・視点・方法を知る。", "特記事項": "本授業科目は、“オンライン授業60単位制限対象科目”ではありません。 The course is not subject to the 60-credit limit for online courses.", "関連科目": "", "授業の概要・背景": "", "授業方法": "教員が知識の詳細について解説したのち、受講生はその知識をふまえて、議論を行う。<br />また自分の学習成果等をまとめて課題を行ったり、レジュメを作成し発表したりする。", "トピック": {"第1回": ["ガイダンス、演習の基本的な枠組み", "教科書の該当する部分を読み、理解を深める。<br />課題をこなしたりレジュメを作成したりする。"], "第2回": ["社会学への招待―「あたりまえ」を疑う大切さ―", "教科書の該当する部分を読み、理解を深める。<br />課題をこなしたりレジュメを作成したりする。"], "第3回": ["自我―僕が僕であるために―", "教科書の該当する部分を読み、理解を深める。<br />課題をこなしたりレジュメを作成したりする。"], "第4回": ["コミュニケーション―僕たちの「想い」は伝わるのか？―", "教科書の該当する部分を読み、理解を深める。<br />課題をこなしたりレジュメを作成したりする。"], "第5回": ["恋愛―二人をつなぐ赤い糸（コミュニケーション・メディア）―", "教科書の該当する部分を読み、理解を深める。<br />課題をこなしたりレジュメを作成したりする。"], "第6回": ["ジェンダー―男であること・女であること―", "教科書の該当する部分を読み、理解を深める。<br />課題をこなしたりレジュメを作成したりする。"], "第7回": ["家族―アニメ、テレビドラマ、映画にみる家族のかたち―", "教科書の該当する部分を読み、理解を深める。<br />課題をこなしたりレジュメを作成したりする。"], "第8回": ["教育―学校って何だろう？―", "教科書の該当する部分を読み、理解を深める。<br />課題をこなしたりレジュメを作成したりする。"], "第9回": ["仕事・産業―これからの社会における「承認」のゆくえ―", "教科書の該当する部分を読み、理解を深める。<br />課題をこなしたりレジュメを作成したりする。"], "第10回": ["行為―僕たちは「自由に」行為できるのか？―", "教科書の該当する部分を読み、理解を深める。<br />課題をこなしたりレジュメを作成したりする。"], "第11回": ["メディアと視聴者―私たちはテレビドラマをどう見ているのか？―", "教科書の該当する部分を読み、理解を深める。<br />課題をこなしたりレジュメを作成したりする。"], "第12回": ["文化―虚構と実在が同期化するアイドル―", "教科書の該当する部分を読み、理解を深める。<br />課題をこなしたりレジュメを作成したりする。"], "第13回": ["テーマパーク―トランスナショナル・ディズニー―", "教科書の該当する部分を読み、理解を深める。<br />課題をこなしたりレジュメを作成したりする。"], "第14回": ["都市―私たちが生きる都市のすがた―", "教科書の該当する部分を読み、理解を深める。<br />課題をこなしたりレジュメを作成したりする。"], "第15回": ["モバイル・ライブズ―これからの私たちの社会のすがた、これからの私たちの生きるかたち―<br />まとめ―社会の大きな力と僕たちの交差点で―", "教科書の該当する部分を読み、理解を深める。<br />課題をこなしたりレジュメを作成したりする。"]}, "評価": {"1": ["", ""], "2": ["", ""], "3": ["", ""], "4": ["", ""], "5": ["", ""], "6": ["", ""], "7": ["", ""], "8": ["", ""], "9": ["", ""], "10": ["", ""], "11": ["", ""], "12": ["", ""], "13": ["", ""], "14": ["", ""], "15": ["", ""], "0": ["", "", "", "", "", ""], "成績評価Grading0": ["種別　Type備考　Note", "割合　Percentage", "評価基準等　Grading Criteria etc."], "成績評価Grading1": ["平常リポート／Individual reports (04)", "100 %", "演習内で提出される質問・感想、課題、レポート等から総合的に評価する。【申請によりオンライン受講を許可された学生に対しては、成績評価についてもオンラインでの対応を行う。】"], "項番No.0": [], "項番No.1": ["2023年度", "春学期／Spring", "月曜３時限／Monday 3", "春学期／Spring", "Ｅ－２０２"]}, "campas": 0, "name": "【200】インターミディエイト演習　１３／Intermediate Seminar", "管理部署": 2, "単位数": 2, "担当者": "遠藤　英樹（ENDO HIDEKI） ", "履修基準年度": "２年", "履修登録方法": "申込制", "緊急授業形態": 0, "オンライン授業形態": 1, "時限1": 2, "評価1": 3, "開講期": 1}