{"履修期": "秋学期", "主な教授言語": "日本語", "授業目的": "　この講義は、「福祉」という営みを、社会学的視点を用いて捉え直すことを目的とする。<BR/>　わたしたちの暮らす社会で、「福祉を必要とする人びと」はどのような位置に置かれているだろうか。また、かれらの生を支援する実践は、どのように語られ、議論されているだろうか。<BR/>　このような観点から、本講義は、「社会福祉」と呼ばれるさまざまな実践の社会的な意義を踏まえ、特に、障害者の生（生存と生活）に着目する。可能な限り具体的な事例を取り上げながら、より現実的な「社会福祉」観を確立することを目指す。", "到達目標": "- 受講者それぞれがより具体的な「福祉」のイメージを確立できる。<BR/>-「障害者が被る社会的障壁」の実態を知り、理解することができる。<BR/>- 日常世界で取り交わされる相互行為を、より大きな社会的文脈のなかに位置づけることができる。", "授業方法": "【対面講義】<BR/>・教員の作成したスライドを用いて講義する。<BR/>・映像資料など適宜使用する。", "トピック": {"第1回": ["ガイダンス : <BR/>講義の概要と成績評価方法の説明", ""], "第2回": ["社会的なものとしての身体 /<BR/>社会関係のなかから「身体」を捉える視点を獲得する。", ""], "第3回": ["障害とはなにか /<BR/>障害者が経験する不利益をどのように捉えるか、基本的な視座である「障害の社会モデル」を理解する。", ""], "第4回": ["障害と合理的配慮 /<BR/>障害の社会モデルを踏まえた社会的な配慮のありかたを理解する。", ""], "第5回": ["配慮の平等 /<BR/>合理的配慮の必要性を「配慮の平等」という観点から考える。", ""], "第6回": ["配慮を得ながら地域で暮らす /<BR/>社会的な支援を得ながら地域で暮らすことの実態と課題を理解する。", ""], "第7回": ["中間レポート", ""], "第8回": ["身体へのまなざしと権力 1 : 生を管理する /<BR/>現代社会における優生思想について理解する。", ""], "第9回": ["身体へのまなざしと権力 2 : 障害と「優生」 /<BR/>福祉国家と優生思想の関係について理解する。", ""], "第10回": ["障害者文化という視角 1 : ろう文化 /<BR/>「ろう文化」の意義について理解する。", ""], "第11回": ["障害者文化という視角 2 : 障害者の暮らしかたと「文化」 /<BR/>障害者に特有の暮らしかたや感覚を「文化」として捉えることの意義を理解する。", ""], "第12回": ["障害とアイデンティティ 1: 軽度障害者 /<BR/>軽度障害者の実態を通じて、障害者のアイデンティティのありかたを理解する。", ""], "第13回": ["障害とアイデンティティ 2: 「健常者」とはだれか /<BR/>障害者文化を検討することを通して、そのネガとしての「健常者」という立場について検討する。", ""], "第14回": ["期末レポート", ""], "授業外学習2": "参考文献や授業中に紹介する本を積極的に読むことを期待する。"}, "評価": {"参考書/Reference books0": ["著者名\nAuthor", "タイトル\nTitle", "発行所\nPublisher", "出版年\nYear of Publication", "ISBN", "ボタン\nButton"], "参考書/Reference books1": ["渡辺一史", "なぜ人と人は支え合うのか", "ちくまプリマー新書", "2018 年", "9784480683434", ""], "参考書/Reference books2": ["石川准", "アイデンティティ・ゲーム : 存在証明の社会学", "新評論", "1992 年", "9784794801418", ""], "参考書/Reference books3": ["川島聡, 飯野由里子, 西倉実季, 星加良司", "合理的配慮 : 対話を開く 対話が拓く", "有斐閣", "2016 年", "9784641174221", ""], "成績評価Grading0": ["種別　Type備考　Note", "割合　Percentage", "評価基準等　Grading Criteria etc."], "成績評価Grading1": ["平常リポート／Individual reports (04)", "60 %", "各回で出される課題 (申請によりオンライン受講を許可された学生に対しては、成績評価についてもオンラインでの対応を行う。)"], "成績評価Grading2": ["その他／Others (99)", "40 %", "中間+期末 2回のレポート (申請によりオンライン受講を許可された学生に対しては、成績評価についてもオンラインでの対応を行う。)"], "更新日時/Date of Update0": "2021年03月12日 12時18分01秒", "項番No.0": [], "項番No.1": ["2021年度", "秋学期／Fall", "火曜５時限／Tuesday 5", "秋学期／Fall", "社－１０１"]}, "開講キャンパス": "西宮上ケ原キャンパス／Nishinomiya Uegahara Campus", "【科目ナンバー/Course Number】授業名称": "【200】福祉社会学／Welfare Sociology", "管理部署": "社会学部／School of Sociology", "単位数": "2", "担当者": "前田　拓也（MAEDA TAKUYA） ", "履修基準年度": "１年", "時限1": "火曜５時限／Tuesday 5", "開講期": "秋学期／Fall"}