{"履修期": "通年", "主な教授言語": "日本語", "授業目的": "研究演習Iと連動して、卒論作成に必須の知識・技術の習得をめざす。", "到達目標": "各自が卒論研究を進めることができるだけの、社会心理学に関する基礎知識とデータ分析の基本技術を習得させる。", "授業方法": "演習形式で実際のデータ収集とその分析の実習を行う。", "トピック": {"第1回": ["データ収集グループの形成、研究テーマの発掘", ""], "授業計画1": "各自の研究テーマとそれに関する先行研究の報告、ディスカッションをおこなう。", "授業外学習2": "演習形式で実際のデータ収集とその分析を実施させる。"}, "評価": {"教科書/Required texts0": ["著者名\nAuthor", "タイトル\nTitle", "発行所\nPublisher", "出版年\nYear of Publication", "ISBN", "ボタン\nButton"], "教科書/Required texts1": ["亀田達也・村田光二", "複雑さに挑む社会心理学", "有斐閣アルマ", "2010 年", "", ""], "成績評価Grading0": ["種別　Type備考　Note", "割合　Percentage", "評価基準等　Grading Criteria etc."], "成績評価Grading1": ["平常リポート／Individual reports (04)", "85 %", "卒論テーマの決定、それに関する基本的な文献の報告レポートと卒論実験（調査）の計画書の提出をもって成績評価をおこなう。"], "成績評価Grading2": ["その他／Others (99)", "15 %", "出欠状況"], "更新日時/Date of Update0": "2021年04月27日 11時53分34秒", "項番No.0": [], "項番No.1": ["2021年度", "通年／Year Round", "火曜４時限／Tuesday 4", "通年／Year Round", "社会心理実験準備室"]}, "開講キャンパス": "西宮上ケ原キャンパス／Nishinomiya Uegahara Campus", "【科目ナンバー/Course Number】授業名称": "【300】実験実習　１／Supervised Research in Social Psychology", "管理部署": "社会学部／School of Sociology", "単位数": "2", "担当者": "野波　寛（NONAMI HIROSHI） ", "履修基準年度": "３年", "時限1": "火曜４時限／Tuesday 4", "開講期": "通年／Year Round"}