{"履修期": "秋学期", "主な教授言語": "日本語", "授業目的": "この授業の目的は、多様なアクティビティを通じて、読解力や様々なリーディングスキルを身につけることです。また、スピーキングやライティングといったアウトプットにつなげる力を養うことも目的とします。", "到達目標": "英語の読解力や様々なリーディングのスキルを身につける。スピーキング、ライティングといったアウトプットにつなげる力も養う。", "授業方法": "Zoomを用いてリアルタイムのオンライン授業を実施する。Zoom URLはLUNAに掲載する。", "トピック": {"第1回": ["ガイダンスとイントロダクション<BR/>授業方法や評価方法などの説明をする。", "事前学習：シラバスをよく読んでおくこと。<BR/>事後学習：授業内で言われたことをしっかりと理解する。"], "第2回": ["Health &amp; Medical IssuesのListening箇所をする。", "事前学習：指定された箇所の予習をする。復習テストにむけて勉強する。<BR/>事後学習：授業で分からなかった箇所、曖昧だった箇所を確認・復習する。"], "第3回": ["Health &amp; Medical IssuesのReading箇所をする。", "事前学習：指定された箇所の予習をする。復習テストにむけて勉強する。<BR/>事後学習：授業で分からなかった箇所、曖昧だった箇所を確認・復習する。"], "第4回": ["Economy &amp; IndustryのListening箇所をする。", "事前学習：指定された箇所の予習をする。復習テストにむけて勉強する。<BR/>事後学習：授業で分からなかった箇所、曖昧だった箇所を確認・復習する。"], "第5回": ["Economy &amp; IndustryのReading箇所をする。", "事前学習：指定された箇所の予習をする。復習テストにむけて勉強する。<BR/>事後学習：授業で分からなかった箇所、曖昧だった箇所を確認・復習する。"], "第6回": ["Economy &amp; Industryに関して作成した問題を基に、復習Quizを行う。<BR/>トピックに関連した質問について自分の意見を述べる。", "事前学習：指定された箇所の予習をする。復習テストにむけて勉強する。<BR/>事後学習：授業で分からなかった箇所、曖昧だった箇所を確認・復習する。"], "第7回": ["Legal IssuesのListening箇所をする。", "事前学習：指定された箇所の予習をする。復習テストにむけて勉強する。<BR/>事後学習：授業で分からなかった箇所、曖昧だった箇所を確認・復習する。"], "第8回": ["Legal IssuesのReading箇所をする。", "事前学習：指定された箇所の予習をする。復習テストにむけて勉強する。<BR/>事後学習：授業で分からなかった箇所、曖昧だった箇所を確認・復習する。"], "第9回": ["Legal Issuesに関して作成した問題を基に、復習Quizを行う。<BR/>トピックに関連した質問について自分の意見を述べる。", "事前学習：指定された箇所の予習をする。復習テストにむけて勉強する。<BR/>事後学習：授業で分からなかった箇所、曖昧だった箇所を確認・復習する。"], "第10回": ["Science &amp; TechnologyのListening箇所をする。", "事前学習：指定された箇所の予習をする。復習テストにむけて勉強する。<BR/>事後学習：授業で分からなかった箇所、曖昧だった箇所を確認・復習する。"], "第11回": ["Science &amp; TechnologyのReading箇所をする。", "事前学習：指定された箇所の予習をする。復習テストにむけて勉強する。<BR/>事後学習：授業で分からなかった箇所、曖昧だった箇所を確認・復習する。"], "第12回": ["Science &amp; Technologyに関して作成した問題を基に、復習Quizを行う。<BR/>トピックに関連した質問について自分の意見を述べる。", "事前学習：指定された箇所の予習をする。復習テストにむけて勉強する。<BR/>事後学習：授業で分からなかった箇所、曖昧だった箇所を確認・復習する。"], "第13回": ["第2回から12回までの内容について試験を実施する。", "事前学習：最終試験にむけて勉強する。<BR/>事後学習：試験で解けなかった箇所、曖昧だった箇所を確認・復習する。"], "第14回": ["秋学期の授業に関して振り返りを行い、ポートフォリオを完成させる。", "事前学習：ポートフォリオ作成のために、これまでの学習を振り返る。<BR/>事後学習：授業で学んだことを再度確認し、復習する。"]}, "評価": {"教科書/Required texts0": ["著者名\nAuthor", "タイトル\nTitle", "発行所\nPublisher", "出版年\nYear of Publication", "ISBN", "ボタン\nButton"], "教科書/Required texts1": ["VELC研究会教材開発グループ / 靜哲人 / 望月正道 / 熊澤孝昭", "AMBITIONS: Intermediate ４技能統合型で学ぶ英語コース： 中級編", "金星堂", "2018 年", "9784764740563", ""], "成績評価Grading0": ["種別　Type備考　Note", "割合　Percentage", "評価基準等　Grading Criteria etc."], "成績評価Grading1": ["平常リポート／Individual reports (04)", "25 %", ""], "成績評価Grading2": ["その他／Others (99)", "75 %", "小テスト（35%）、グループワーク参加度、積極性（30%）、ポートフォリオ（10%）"], "成績評価Grading3": "備考　Note\nZoomのブレイクアウトルーム機能を使ってグループワークを行います。", "備考Note0": "進度などは状況に応じて変更することもあります。", "更新日時/Date of Update1": "2021年09月09日 08時14分52秒", "項番No.0": [], "項番No.1": ["2021年度", "秋学期／Fall", "水曜２時限／Wednesday 2", "秋学期／Fall", "Ａ－２０５"]}, "campas": 0, "name": "【200】英語IIＡ（LR）　９／English II A(Listening & Reading) ", "管理部署": 3, "単位数": 1, "担当者": "西　美都子（NISHI MITSUKO） ", "履修基準年度": "２年", "授業形態": 1, "緊急授業形態": 1, "オンライン授業形態": 1, "時限1": 15, "評価1": 3, "評価2": 4, "開講期": 2}