{"履修期": "通年", "主な教授言語": "日本語", "授業目的": "本演習の目的は、マーケティングリサーチに基づく、新製品開発及びマーケティング戦略の立案する能力を身につけることである。", "到達目標": "到達目標は、受講生が、マーケティング・リサーチの理論、技術、創造力をもとに、精度の高いマーケティング戦略を立案、実行できるようになることである。", "授業方法": "【授業形態】授業形態は、その時点の状況を踏まえemailで連絡を行うが、基本的に対面とオンライン併用で行う。<BR/>他大学ゼミとの競合プレゼンに向けて、グループで、アイデア想起から製品化・販売のための戦略立案までの提案を考え、ゼミで報告・議論を行う。競合プレゼンで優れた製品案戦略案を提案するため、教科書を用いてマーケティング理論、消費者行動論の学習や、ケース・スタディを行う。<BR/>　基礎疾患等によりオンライン授業の受講を大学から許可された学生（以下、配慮対象学生）には、Zoom URLを連絡し、オンラインで授業を受けることができるよう配慮する。配布資料は、他の受講生と同様にLunaからダウンロードすること。ただし、オンラインで受講する場合、板書内容は見えにくい可能性がある。この点ご了解いただきたい。", "トピック": {"第1回": ["セッション１：マーケティング戦略１", "教科書の予習・復習、ケース資料の検討"], "第2回": ["セッション１：ケーススタディ１", "ケースの予習・復習"], "第3回": ["セッション２：マーケティング戦略２", "教科書の予習・復習、ケース資料の検討"], "第4回": ["セッション２：ケース・スタディ", "ケースの予習・復習"], "第5回": ["セッション３：消費者行動の理論と分析", "教科書の予習・復習、ケース資料の検討"], "第6回": ["セッション３：ケース・スタディ", "ケースの予習・復習"], "第7回": ["セッション４：マーケティング戦術１", "教科書の予習・復習、ケース資料の検討"], "第8回": ["セッション４：ケース・スタディ", "ケースの予習・復習"], "第9回": ["新製品開発実習１", "質的調査の実施"], "第10回": ["新製品開発実習１", "量的調査の実施"], "第11回": ["新製品開発実習１", "データ分析"], "第12回": ["セッション５：マーケティング戦術２", "教科書の予習・復習、ケース資料の検討"], "第13回": ["セッション５：ケース・スタディ", "ケースの予習・復習"], "第14回": ["グループ・プレゼンテーション１", "報告準備、報告後の事後検討"], "第15回": ["グループ・プレゼンテーション２", "報告準備、報告後の事後検討"], "第16回": ["グループ・プレゼンテーション３", "報告準備、報告後の事後検討"], "第17回": ["実務家による講演", "事前配布資料による予習"], "第18回": ["グループ・プレゼンテーション４", "報告準備、報告後の事後検討"], "第19回": ["グループ・プレゼンテーション５", "報告準備、報告後の事後検討"], "第20回": ["グループ・プレゼンテーション６", "報告準備、報告後の事後検討"], "第21回": ["グループ・プレゼンテーション７", "報告準備、報告後の事後検討"], "第22回": ["グループ・プレゼンテーション８", "報告準備、報告後の事後検討"], "第23回": ["グループ・プレゼンテーション９", "報告準備、報告後の事後検討"], "第24回": ["セッション６：マーケティング戦術３", "教科書の予習・復習、ケース資料の検討"], "第25回": ["セッション６：ケース・スタディ", "ケースの予習・復習"], "第26回": ["セッション７：マーケティング戦術４", "教科書の予習・復習、ケース資料の検討"], "第27回": ["セッション７：ケース・スタディ", "ケースの予習・復習"], "第28回": ["セッション８：マーケティング戦術５", "教科書の予習・復習、ケース資料の検討"], "授業外学習2": "産学連携・大学横断の新製品提案コンテストに参加する予定である。他大学ゼミとの競合プレゼンに向けて、グループで、アイデア想起から製品化・販売のための戦略立案までの提案を考え、ゼミで報告・議論を行う。そのために、授業外の時間にグループワークを行うことが必要である<BR/>また、上記の新製品開発を実際に行うため、教科書を用いマーケティング理論、消費者行動論の学習、戦略策定を仮想的に経験するケース・スタディを行う。これらに関する予習、プレゼン準備も必要である。"}, "評価": {"教科書/Required texts0": ["著者名\nAuthor", "タイトル\nTitle", "発行所\nPublisher", "出版年\nYear of Publication", "ISBN", "ボタン\nButton"], "教科書/Required texts1": ["小川孔輔", "マーケティング入門", "日本経済新聞社", "2009 年", "978-4532133696", ""], "参考書/Reference books0": ["著者名\nAuthor", "タイトル\nTitle", "発行所\nPublisher", "出版年\nYear of Publication", "ISBN", "ボタン\nButton"], "参考書/Reference books1": ["青木幸弘", "消費者行動の知識", "日経文庫", "2010 年", "", ""], "参考書/Reference books2": ["杉本徹雄編", "新・消費者理解のための心理学", "福村出版", "2012 年", "", ""], "参考書/Reference books3": ["高田博和他", "マーケティングリサーチ入門", "ＰＨＰ研究所", "2008 年", "", ""], "参考書/Reference books4": ["田中洋", "課題解決！マーケティング・リサーチ入門", "ダイヤモンド社", "2010 年", "", ""], "参考書/Reference books5": ["古川一郎、守口剛、阿部誠", "マーケティング・サイエンス入門[新版]", "有斐閣", "2011 年", "", ""], "学生による授業評価の方法Course Evaluation by Students0": "授業中実施", "成績評価Grading0": ["種別　Type備考　Note", "割合　Percentage", "評価基準等　Grading Criteria etc."], "成績評価Grading1": ["平常リポート／Individual reports (04)", "50 %", ""], "成績評価Grading2": ["その他／Others (99)", "50 %", "議論への貢献、グループワークへの貢献、プレゼンテーション"], "成績評価Grading3": "備考　Note\n配慮対象学生の成績評価は、他の学生と同様に行う。\n【平時】上記に同じ\n【オンライン受講生対象】上記に同じ", "更新日時/Date of Update0": "2021年10月27日 00時38分11秒", "項番No.0": [], "項番No.1": ["2021年度", "通年／Year Round", "月曜４時限／Monday 4", "通年／Year Round", "Ｄ－３０５"]}, "campas": 0, "name": "【350】研究演習I　２／Seminar I", "管理部署": 5, "単位数": 4, "担当者": "石淵　順也（ISHIBUCHI JUNYA） ", "履修基準年度": "３年", "授業形態": 0, "緊急授業形態": 1, "オンライン授業形態": 1, "時限1": 3, "評価1": 3, "評価2": 4, "開講期": 0}