{"履修期": "通年", "主な教授言語": "日本語", "授業目的": "最新の英文雑誌の中から機能性高分子や有機分子に関する論文のいくつかを選択し、内容をまとめた上で研究会において発表することで有機化学の知識を習得する。", "到達目標": "英文論文の内容を理解するのみならず、他の人が理解できるように紹介すること。", "授業方法": "研究会において輪講形式で実施する", "トピック": {"授業計画1": "各自に与えられたテーマに関連した英文論文や書籍を要約かつ紹介する。", "授業外学習2": "関連する文献や書籍の通読。発表資料の作成。"}, "評価": {"学生による授業評価の方法Course Evaluation by Students0": "授業中実施", "成績評価Grading0": ["種別　Type備考　Note", "割合　Percentage", "評価基準等　Grading Criteria etc."], "成績評価Grading1": ["その他／Others (99)", "100 %", "論文内容の理解度や、発表資料の完成度から評価する。"], "更新日時/Date of Update0": "2021年01月15日 16時28分48秒", "項番No.0": [], "項番No.1": ["2021年度", "通年／Year Round", "集中・その他／Concentration/Other", "通年／Year Round", "教室未定"]}, "campas": 1, "name": "【401】外国書講読　４４／Reading Seminar of Foreign Literature", "管理部署": 6, "単位数": 2, "担当者": "森崎　泰弘（MORISAKI YASUHIRO） ", "履修基準年度": "４年", "時限1": 49, "評価1": 4, "開講期": 0}