{"履修期": "春学期", "主な教授言語": "日本語", "授業目的": "<p class=\"MsoNormal\"><span ｍｓ=\"ｍｓ\" ｐゴシック\";mso-ansi-language:en-us;\"=\"ｐゴシック';mso-ansi-language:en-us;'\" style=\"font-size:12.0pt;font-family:;\">本演習の目的は、学生諸君が外務省ホームページ等の公開情報により今日の国際政治経済問題についての理解を深め、分析能力を習得することである。</span></p>", "到達目標": "<p class=\"MsoNormal\"><span ｍｓ=\"ｍｓ\" ｐゴシック\";mso-ansi-language:en-us;\"=\"ｐゴシック';mso-ansi-language:en-us;'\" style=\"font-size:12.0pt;font-family:;\">学生諸君は、</span></p>\n\n<p class=\"MsoNormal\"><span ｍｓ=\"ｍｓ\" ｐゴシック\";mso-ansi-language:en-us;\"=\"ｐゴシック';mso-ansi-language:en-us;'\" style=\"font-size:12.0pt;font-family:;\">・外務大臣記者会見等の公開情報を通じ最新の外交テーマに関する知見を深めることができ、</span></p>\n\n<p class=\"MsoNormal\"><span ｍｓ=\"ｍｓ\" ｐゴシック\";mso-ansi-language:en-us;\"=\"ｐゴシック';mso-ansi-language:en-us;'\" style=\"font-size:12.0pt;font-family:;\">・当該テーマに関する新聞論調等を整理し、必要な論点を自ら発見することができ、</span></p>\n\n<p class=\"MsoNormal\"><span ｍｓ=\"ｍｓ\" ｐゴシック\";mso-ansi-language:en-us;\"=\"ｐゴシック';mso-ansi-language:en-us;'\" style=\"font-size:12.0pt;font-family:;\">・最終的には国際問題に関して自ら政策分析を行うことができる視座を身につけることができる。</span></p>", "特記事項": "", "関連科目": "総合政策学部で開講されている国際関連科目", "授業の概要・背景": "", "授業方法": "ゼミナール方式　Seminar Class<div>【現役外交官等をゲストスピーカーで招くことも検討】<br /><div><br /></div></div>", "トピック": {"第1回": ["<p class=\"MsoNormal\"><span style=\"font-size:12pt;\">１４回すべて対面授業で実施</span></p><p class=\"MsoNormal\"><span style=\"font-size:12pt;\">オリエンテーション：国際政治、国際経済を見るうえで必要な視座</span></p>", ""], "第2回": ["<p class=\"MsoNormal\"><span ｍｓ=\"ｍｓ\" ｐゴシック\";mso-ansi-language:en-us;\"=\"ｐゴシック';mso-ansi-language:en-us;'\" style=\"font-size:12.0pt;font-family:;\">カレント・トピックの紹介①：発表、討論</span></p>", "発表の準備"], "第3回": ["<p class=\"MsoNormal\"><span ｍｓ=\"ｍｓ\" ｐゴシック\";mso-ansi-language:en-us;\"=\"ｐゴシック';mso-ansi-language:en-us;'\" style=\"font-size:12.0pt;font-family:;\">カレント・トピックの紹介②：発表、討論</span></p>", "発表の準備"], "第4回": ["<p class=\"MsoNormal\"><span ｍｓ=\"ｍｓ\" ｐゴシック\";mso-ansi-language:en-us;\"=\"ｐゴシック';mso-ansi-language:en-us;'\" style=\"font-size:12.0pt;font-family:;\">日本外交の基礎【FOIP、環太平洋諸国との関係（開かれた地域主義）、国際紛争への対応】</span></p>", ""], "第5回": ["<p class=\"MsoNormal\"><span ｍｓ=\"ｍｓ\" ｐゴシック\";mso-ansi-language:en-us;\"=\"ｐゴシック';mso-ansi-language:en-us;'\" style=\"font-size:12.0pt;font-family:;\">発表、討論①</span></p>", "発表の準備"], "第6回": ["<p class=\"MsoNormal\"><span ｍｓ=\"ｍｓ\" ｐゴシック\";mso-ansi-language:en-us;\"=\"ｐゴシック';mso-ansi-language:en-us;'\" style=\"font-size:12.0pt;font-family:;\">発表、討論②</span></p>", "発表の準備"], "第7回": ["<p class=\"MsoNormal\"><span ｍｓ=\"ｍｓ\" ｐゴシック\";mso-ansi-language:en-us;\"=\"ｐゴシック';mso-ansi-language:en-us;'\" style=\"font-size:12.0pt;font-family:;\">自由貿易体制と経済安全保障【WTOは機能するか、TPP、各国の保護主義】</span></p>", ""], "第8回": ["<span ｍｓ=\"ｍｓ\" ｐゴシック\";font-size:16px;\"=\"ｐゴシック';font-size:16px;'\" style=\"font-family:;\">発表、討論①</span>", "発表の準備"], "第9回": ["<span ｍｓ=\"ｍｓ\" ｐゴシック\";font-size:16px;\"=\"ｐゴシック';font-size:16px;'\" style=\"font-family:;\">発表、討論②</span>", "発表の準備"], "第10回": ["<p class=\"MsoNormal\"><span ｍｓ=\"ｍｓ\" ｐゴシック\";mso-ansi-language:en-us;\"=\"ｐゴシック';mso-ansi-language:en-us;'\" style=\"font-size:12.0pt;font-family:;\">国際問題をどう分析するか【分析に必要な「立ち位置」、地政学・地経学の視点】</span></p>", ""], "第11回": ["<span ｍｓ=\"ｍｓ\" ｐゴシック\";font-size:16px;\"=\"ｐゴシック';font-size:16px;'\" style=\"font-family:;\">発表、討論①</span>", "発表の準備"], "第12回": ["<span ｍｓ=\"ｍｓ\" ｐゴシック\";font-size:16px;\"=\"ｐゴシック';font-size:16px;'\" style=\"font-family:;\">発表、討論②</span>", "発表の準備"], "第13回": ["<span ｍｓ=\"ｍｓ\" ｐゴシック\";font-size:16px;\"=\"ｐゴシック';font-size:16px;'\" style=\"font-family:;\">発表、討論③</span>", "発表の準備"], "第14回": ["<p class=\"MsoNormal\"><span ｍｓ=\"ｍｓ\" ｐゴシック\";mso-ansi-language:en-us;\"=\"ｐゴシック';mso-ansi-language:en-us;'\" style=\"font-size:12.0pt;font-family:;\">全体総括</span></p>", ""]}, "評価": {"1": ["", ""], "2": ["", ""], "3": ["", ""], "4": ["", ""], "5": ["", ""], "6": ["", ""], "7": ["", ""], "8": ["", ""], "9": ["", ""], "10": ["", ""], "11": ["", ""], "12": ["", ""], "13": ["", ""], "14": ["", ""], "成績評価Grading0": ["種別　Type備考　Note", "割合　Percentage", "評価基準等　Grading Criteria etc."], "成績評価Grading1": ["平常リポート／Individual reports (04)", "70 %", "最終発表（第１１－１３回）を含む発表、レポート"], "成績評価Grading2": ["授業への参加度（自発性、積極性、主体性、等）／In-class participation,contribution (09)", "30 %", ""], "項番No.0": [], "項番No.1": ["2024年度", "春学期／Spring", "木曜３時限／Thursday 3", "春学期／Spring", "Ｉ－１０１"]}, "campas": 1, "name": "【200】国際政策演習　４／Seminar in International Policy Studies", "管理部署": 7, "単位数": 2, "担当者": "渋谷　和久（SHIBUYA KAZUHISA） ", "履修基準年度": "２年", "履修登録方法": "申込制", "緊急授業形態": 0, "時限1": 23, "評価1": 3, "評価2": 5, "開講期": 1, "成績評価備考": "割合　Percentage"}