{"履修期": "通年", "主な教授言語": "日本語", "授業目的": "　メディア工房では、本格的なメディア制作にあたり、学外の制作集団やウエッブTV局と連携しながら、ウエッブTV番組の企画とライブ配信を実践し、実際のメディア制作における共同作業の意義を理解します。", "到達目標": "　メディア工房では、本格的なメディア制作にあたり、学外の制作集団やウエッブTV局と連携しながら、ウエッブTV番組の企画とライブ配信を実践し、実際のメディア制作における共同作業の意義を理解します。", "授業方法": "2020年度春学期は、新型コロナ肺炎ウイルスに対する感染防護のために、オンライン手法をもちいた授業を行う場合があります。科目情報に注意してください。<BR/>このシラバスは、あくまで例年の内容を記したものです。今年度の進め方については、LINEのグループをつうじてのご連絡を参照ください。<BR/>平常授業にもどったときは、教室での学習と討議、並行して、メディア実験室の機材を使って、素材の編集や構成を個別指導します。", "トピック": {"第1回": ["", "双方向オンライン授業で実施する場合があります。詳細は、lineでお知らせします。"], "第2回": ["", "双方向オンライン授業で実施する場合があります。詳細は、lineでお知らせします。"], "第3回": ["", "双方向オンライン授業で実施する場合があります。詳細は、lineでお知らせします。"], "第4回": ["", "双方向オンライン授業で実施する場合があります。詳細は、lineでお知らせします。"], "第5回": ["", "双方向オンライン授業で実施する場合があります。詳細は、lineでお知らせします。"], "第6回": ["", "双方向オンライン授業で実施する場合があります。詳細は、lineでお知らせします。"], "第7回": ["", "双方向オンライン授業で実施する場合があります。詳細は、lineでお知らせします。"], "第8回": ["", "双方向オンライン授業で実施する場合があります。詳細は、lineでお知らせします。"], "第9回": ["", "双方向オンライン授業で実施する場合があります。詳細は、lineでお知らせします。"], "第10回": ["", "双方向オンライン授業で実施する場合があります。詳細は、lineでお知らせします。"], "第11回": ["", "双方向オンライン授業で実施する場合があります。詳細は、lineでお知らせします。"], "第12回": ["", "双方向オンライン授業で実施する場合があります。詳細は、lineでお知らせします。"], "第13回": ["", "双方向オンライン授業で実施する場合があります。詳細は、lineでお知らせします。"], "第14回": ["", "双方向オンライン授業で実施する場合があります。詳細は、lineでお知らせします。"], "授業計画1": "　講義科目ではありませんので、各回ごとの授業内容というような、あらかじめ定められた枠組みはありません。しかし、おおむね以下のような流れで進行させていくつもりです。まず、最終目標として、１５分程度のラジオ番組の制作を体験し、４回生での本格的な卒業研究制作に備えるという目標を設定します。<BR/>　この目標に向けて、ゼミ全体でシリーズ番組を課題を決め、その統一課題にそって、テーマのリサーチ、取材、インタビュー、録音素材の編集、番組構成、スタジオでの番組収録という流れで、番組制作を体験していきます。<BR/>　今年のシリーズ番組のテーマは、授業開始時に決定しますが、この全体テーマにそって、それぞれ個別テーマをきめ、取材対象者を選び、アポイントをとり、インタビューを行い、録音と編集を行い、１５分の番組に仕上げます。<BR/>　秋学期では、上述したように、学外の制作集団やウエッブTV局と連携しながら、９回にわたって、ウエッブTV番組の企画とライブ配信を実践し、実際のメディア制作における共同作業を体験します。", "授業外学習2": "ライブストリーミングに関する技能に各自習熟しておいてください。"}, "評価": {"教科書/Required texts0": ["著者名\nAuthor", "タイトル\nTitle", "発行所\nPublisher", "出版年\nYear of Publication", "ISBN", "ボタン\nButton"], "教科書/Required texts1": ["山中速人　編著", "マルチメディアでフィールドワーク", "有斐閣", "2002 年", "4641076537", ""], "参考文献・資料Reference books0": "とくにありません。", "学生による授業評価の方法Course Evaluation by Students0": "授業中実施", "成績評価Grading0": ["種別　Type備考　Note", "割合　Percentage", "評価基準等　Grading Criteria etc."], "成績評価Grading1": ["その他／Others (99)", "100 %", "授業参加および制作番組の完成度"], "成績評価Grading2": "備考　Note\n学習への参加と各人の課題にどれだけ深く集中し取り組もうとしているか。また、制作番組の完成度、および担当した番組への貢献度で評価します。", "更新日時/Date of Update0": "2021年02月21日 09時03分43秒", "項番No.0": [], "項番No.1": ["2021年度", "通年／Year Round", "木曜４時限／Thursday 4", "通年／Year Round", "ＩＩＩ－２０７"]}, "開講キャンパス": "神戸三田キャンパス／Kobe Sanda Campus", "【科目ナンバー/Course Number】授業名称": "【400】メディア工房II　９／Media Studio 2", "管理部署": "総合政策学部／School of Policy Studies", "単位数": "4", "担当者": "山中　速人（YAMANAKA HAYATO） ", "履修基準年度": "４年", "時限1": "木曜４時限／Thursday 4", "開講期": "通年／Year Round"}