{"履修期": "秋学期", "主な教授言語": "日本語", "授業目的": "本授業の目的は、履修生が将来のキャリアパスや、ワークライフバランスへの基本的な道筋を理解することにある。", "到達目標": "ゲストの講義に耳を傾け、その行動様式や思考特性などを知ることにより、履修生は自らのキャリアパスを設計することができるようになる。", "特記事項": "", "関連科目": "", "授業の概要・背景": "<span style=\"font-size:13.28px;\">ライフデザインの観点から、問題発見能力と問題解決能力を習得できるよう取り運ぶ。</span>本学の卒業生を中心に、各界で活躍するゲストスピーカーが構築した具体的なキャリアは、履修生の将来設計にとって参考になると思われる。", "授業方法": "ゲストスピーカーによる講義終了後、その内容に基づくミニテストを毎回実施する（資料の持ち込みを認める）。ミニテストの合計点により成績評価を行う。詳細は担当教員によるイントロダクションの際に口頭で説明する。", "トピック": {"第1回": ["<div><span style=\"font-size:13.28px;\">【スタートアップウィーク】オンライン授業（課題提示型・オンデマンド型）《90分》</span></div><div><span style=\"font-size:13.28px;\">担当：木本圭一「イントロダクション」</span></div>", ""], "第2回": ["<div><span style=\"font-size:13.28px;\">【フレックスアワーズ】オンライン授業（課題提示型・オンデマンド型）《90分》</span></div><div><span style=\"font-size:13.28px;\">担当：大木義徳「イントロダクション」</span></div>", ""], "第3回": ["<div><span style=\"font-size:13.28px;\">【フレックスアワーズ】オンライン授業（課題提示型・オンデマンド型）《90分》</span></div><div><span style=\"font-size:13.28px;\">担当：本学キャリアセンター「センターの概要」（仮）</span></div><div><span style=\"font-size:13.28px;\">https://www.kwansei.ac.jp/career/center.html</span></div>", ""], "第4回": ["<div><span style=\"font-size:13.28px;\">【コアウィークス①】9月30日（水）対面授業《90分》担当：木本圭一</span></div><div><span style=\"font-size:13.28px;\">ゲストスピーカーによる特別講義（主に民間部門）※決定次第記載内容更新</span></div>", ""], "第5回": ["【コアウィークス②】10月7日（水）対面授業《90分》担当：木本圭一<div>ゲストスピーカーによる特別講義（主に民間部門）※同上</div>", ""], "第6回": ["<div><span style=\"font-size:13.28px;\">【コアウィークス③】10月14日（水）対面授業《90分》担当：葉佐賢太郎</span></div><div><span style=\"font-size:13.28px;\">ゲストスピーカーによる特別講義（主に民間部門）※同上</span></div>", ""], "第7回": ["【コアウィークス④】10月21日（水）対面授業《90分》担当：木本圭一<div>ゲストスピーカーによる特別講義（主に民間部門）※同上</div>", ""], "第8回": ["【コアウィークス⑤】10月28日（水）対面授業《90分》担当：木本圭一<div>ゲストスピーカーによる特別講義（主に民間部門）※同上</div>", ""], "第9回": ["<div><span style=\"font-size:13.28px;\">【コアウィークス⑥】11月4日（水）対面授業《90分》担当：木本圭一</span></div><div><span style=\"font-size:13.28px;\">ゲストスピーカーによる特別講義（主に民間部門）※同上</span></div>", ""], "第10回": ["【コアウィークス⑦】11月11日（水）対面授業《90分》担当：葉佐賢太郎<div>ゲストスピーカーによる特別講義（主に公共部門）※同上</div>", ""], "第11回": ["<div><span style=\"font-size:13.28px;\">【コアウィークス⑧】11月18日（水）対面授業《90分》担当：大木義徳</span></div><div><span style=\"font-size:13.28px;\">ゲストスピーカーによる特別講義（主に公共部門）※同上</span></div>", ""], "第12回": ["【コアウィークス⑨】11月25日（水）対面授業《90分》担当：大木義徳<div>ゲストスピーカーによる特別講義（主に公共部門）※同上</div>", ""], "第13回": ["<div><span style=\"font-size:13.28px;\">【コアウィークス⑩】12月2日（水）対面授業《90分》担当：大木義徳</span></div><div><span style=\"font-size:13.28px;\">ゲストスピーカーによる特別講義（主に公共部門）※同上</span></div>", ""], "第14回": ["【コアウィークス⑪】12月9日（水）対面授業《90分》担当：葉佐賢太郎<div>ゲストスピーカーによる特別講義（主に公共部門）※同上</div>", ""], "第15回": ["<div><span style=\"font-size:13.28px;\">【コアウィークス⑫】12月16日（水）対面授業《90分》担当：大木義徳</span></div><div><span style=\"font-size:13.28px;\">ゲストスピーカーによる特別講義（主に公共部門）※同上</span></div>", ""], "授業計画1": "毎回のゲストスピーカーは2026年6月末をメドに、決定次第追記する。", "授業外学習2": "<span style=\"font-size:13.28px;\">ゲストスピーカーによる講義内容を振り返りながら、自らのキャリアプランを検討する。</span>"}, "評価": {"教科書/Required texts0": ["授業時に指定する。"], "参考文献・資料/Reference books0": ["授業時に指定する。"], "学生による授業評価の方法Course Evaluation by Students0": ["実施する。"], "学生による授業評価の方法Course Evaluation by Students1": ["各授業科目は、各学部・研究科の定めるディプロマ・ポリシー（DP）・カリキュラム・ポリシー（CP）に基づき、カリキュラム上に配置されています。DP・CPを意識して本授業科目の学修を進めることで、各学部・研究科の期待する以下の能力が養成されます。教養基礎科目（第１類）：１．国際事情に関する課題の理解力と分析力：世界諸地域を人文・社会科学の様々な観点から理解し、分析できる。"], "学生による授業評価の方法Course Evaluation by Students2": ["毎回の授業で実施する。"], "成績評価Grading0": ["種別　Type備考　Note", "割合　Percentage", "評価基準等　Grading Criteria etc."], "成績評価Grading1": ["授業中試験／In-class examination (03)", "100 %", "毎回実施するミニテスト（資料持込可能）の合計点数により評価する。"], "更新日時/Date of Update0": ["2026年03月09日 15時34分46秒"], "項番No.0": [], "項番No.1": ["2026年度", "秋学期／Fall", "水曜４時限／Wednesday 4", "秋学期／Fall", "Ｇ－ＩＳ３０３"]}, "campas": 0, "name": "【100】ライフ・デザイン入門／Introduction to Future Career [JP]", "管理部署": 10, "単位数": 2, "担当者": "木本　圭一（KIMOTO KEIICHI） ", "履修基準年度": "１年", "履修登録方法": "申込制", "開講期": 2, "時限1": 17, "時限1_term": 1, "評価1": 2}