{"履修期": "秋学期集中", "主な教授言語": "日本語", "授業目的": "オーストラリアを中心としたオセアニア地域における政治と外交の特色を理解する。また、日本との間での政治や外交関係にも注目し、われわれにとってこの地域の政治や外交がどのように関わっているのかを知る。", "到達目標": "オセアニアの歴史について、とりわけ近代の植民地化の経緯とその後の政治的・経済的関係についての基礎的な理解を得ることができる。現代のオセアニアを巡る政治と外交の特色を描く様々なトピックを具体的に理解することができる。", "授業方法": "授業は教室で対面実施します。<BR/>オンライン授業申請者にはオンデマンドでの動画配信を行います。", "トピック": {"第1回": ["オセアニアの歴史とその現在", ""], "第2回": ["オセアニアの現在", ""], "第3回": ["オーストラリアの歴史（妙）", ""], "第4回": ["オーストラリアの政治制度", ""], "第5回": ["オーストラリアの政治：多文化主義政策の歴史的背景", ""], "第6回": ["オーストラリアの政治：多文化主義政策の現在１", ""], "第7回": ["オーストラリアと難民政策の歴史的背景", ""], "第8回": ["オーストラリアと難民政策の現在", ""], "第9回": ["オーストラリアの政治：先住民（アボリジニー）政策の歴史的背景", ""], "第10回": ["オーストラリアの政治：先住民（アボリジニー）政策の現在", ""], "第11回": ["オーストラリアの政治：先住民運動", ""], "第12回": ["オーストラリアの外交史", ""], "第13回": ["オーストラリアと日本の外交関係", ""], "第14回": ["まとめ", ""], "授業外学習2": "実施しない予定。"}, "評価": {"成績評価Grading0": ["種別　Type備考　Note", "割合　Percentage", "評価基準等　Grading Criteria etc."], "成績評価Grading1": ["平常リポート／Individual reports (04)", "100 %", "25点満点のレポート課題を4回実施する。"], "備考Note0": "配布する資料や照会する参考文献が英文（原著）の場合があります。ある程度の英文を講読する準備をしておいてください。\n【講義日程】\n2022/2/16,17,18,19\n1日目：４コマ（10:50～18：30まで）\n2日目：4コマ（9:00～16：40まで）\n3日目：4コマ（9:00～16：40まで）\n4日目：２コマ（9:00～12：30まで）", "更新日時/Date of Update1": "2021年10月10日 09時20分20秒", "項番No.0": [], "項番No.1": ["2021年度", "秋学期集中／Intensive (Fall)", "集中・その他／Concentration/Other", "秋学期集中／Intensive (Fall)", "Ｇ－ＩＳ１０８"]}, "campas": 0, "name": "【480】オセアニアの政治と外交／Politics and Diplomacy of Oceania Countries", "管理部署": 10, "単位数": 2, "担当者": "濱野　健（HAMANO TAKESHI） ", "履修基準年度": "２年", "緊急授業形態": 2, "オンライン授業形態": 2, "時限1": 49, "評価1": 3, "開講期": 9}