{"履修期": "春学期", "主な教授言語": "日本語", "授業目的": "都市の路地空間の特徴と構成原理について、建築空間との関係性に着目しながら、事例を踏まえて議論する", "到達目標": "学生が、路地空間の魅力を生かした都市計画や建築設計のデザインへの理解を深めること。", "特記事項": "本授業科目は、“オンライン授業60単位制限対象科目”ではありません。 The course is not subject to the 60-credit limit for online courses.", "関連科目": "比較都市論　都市デザイン論　都市・農村計画", "授業の概要・背景": "世界各地の都市には様々な路地空間が今も存在する。路地空間は防災上の課題を持つ一方で、身近な生活空間として住民に活用されたり、都市の賑わいの場となったりしている。本演習は、路地空間に関する基本的な知識を講義したうえで、学生自らが様々なタイプの路地空間の実態を調べ、建築空間や街区との関係に配慮した計画技法や管理手法等について、グループディスカッションによって、理解を深める。なお定員16名とする。", "授業方法": "各地の路地空間の成立過程や法制度的位置づけなどを講義したうえで、学生自らが各地の事例を収集し、その特徴、構成原理などについて報告し、意見交換する。これをふまえて、路地の魅力を生かした建築デザインやまちづくりの方法をともに考える。", "トピック": {"第1回": ["オリエンテーション：路地とは何か、路地から何を学ぶのか", "次回講義までの準備：世界の路地空間の事例や、路地に関する文学作品、映画、写真、事件、イベント、新聞冊子記事、SNSなどの情報収集。"], "第2回": ["世界の路地：講義、グループ分け", "次回講義までの準備：自らの路地体験を振りかえり、次回発表の準備をする。"], "第3回": ["学生それぞれの路地空間の経験：事例報告", "次回講義までの準備：紹介された事例の確認と振り返り。"], "第4回": ["路地発生のメカニズム：講義", "講義内容の復習"], "第5回": ["路地と街区、路地と建築形態：講義", "講義内容の復習"], "第6回": ["路地の法的位置づけ：講義", "講義内容の復習。次回発表の準備"], "第7回": ["学生による事例発表とディスカッション①：大都市都心の路地と建築", "講義内容の復習。次回発表の準備"], "第8回": ["学生による事例発表とディスカッション②：歴史的市街地の路地と建築", "講義内容の復習。次回発表の準備"], "第9回": ["学生による事例発表とディスカッション③：漁村の路地と建築", "講義内容の復習。次回発表の準備"], "第10回": ["学生による事例発表とディスカッション④：アジア都市の路地と建築", "講義内容の復習。次回発表の準備"], "第11回": ["学生による事例発表とディスカッション⑤：ヨーロッパ都市の路地と建築", "講義内容の復習。次回発表の準備"], "第12回": ["学生による事例発表とディスカッション⑥：イスラム世界の路地と建築", "講義内容の復習。次回発表の準備"], "第13回": ["学生による事例発表とディスカッション⑦：建築の中の路地と建築設計", "講義内容の復習"], "第14回": ["まとめ：路地を活かしたまちづくり：講義", ""]}, "評価": {"参考文献・資料Reference books0": "上田篤・田端修編『路地研究』鹿島出版会\nその他授業中に紹介する。", "学生による授業評価の方法Course Evaluation by Students0": "全学統一様式の「授業に関する調査による", "学位授与の方針との関連Relationship to Diploma Policy1": "各授業科目は、各学部・研究科の定めるディプロマ・ポリシー（DP）・カリキュラム・ポリシー（CP）に基づき、カリキュラム上に配置されています。\nDP・CPを意識して本授業科目の学修を進めることで、各学部・研究科の期待する能力が養成されます。\n各学部・研究科のDP、CPや教育課程表（授業科目一覧等）は、下記リンクこちらに掲載していますので学修計画の参考にしてください。\nhttps://kwic.kwansei.ac.jp/cabinet/reference?typeCd=0&cabinetId=557&directLink=1\n※kwicへのリンクとなります（在学生のみ閲覧可）", "成績評価Grading0": ["種別　Type備考　Note", "割合　Percentage", "評価基準等　Grading Criteria etc."], "成績評価Grading1": ["定期試験に代わるリポート／Term paper to replace the final examination (02)", "60 %", ""], "成績評価Grading2": ["その他／Others (99)", "40 %", "授業中の発表"], "更新日時/Date of Update0": "2023年02月17日 09時52分07秒", "項番No.0": [], "項番No.1": ["2023年度", "春学期／Spring", "月曜２時限／Monday 2", "春学期／Spring", "ＶＩＩＩ－３０４"]}, "campas": 1, "name": "【200】建築・都市演習　７／Practice in Architecture and Urban Studies", "管理部署": 14, "単位数": 2, "担当者": "角野　幸博（KADONO YUKIHIRO） ", "履修基準年度": "２年", "緊急授業形態": 0, "オンライン授業形態": 1, "時限1": 1, "評価1": 1, "評価2": 4, "開講期": 1}