{"履修期": "春学期", "主な教授言語": "英語", "授業目的": "英文欄参照", "到達目標": "英文欄参照", "授業方法": "Face-to-face. Students will participate in daily discussion activities, make presentations, read extensively, and use English in communicative tasks.<BR/><BR/>During the infection priority period, most classes will be held on Zoom. Students should join the Zoom session during the scheduled class time. Some classes might be on campus face-to-face. The instructor will notify at least one week in advance whether class will be online or in person. <BR/><BR/>*This course will be held on campus as a face-to-face lesson. However, if any students for this class have been granted permission to take classes online in 2021 due to health conditions, course materials and on-demand broadcast of data recorded from face-to-face classes will be made available on LUNA.", "トピック": {"第1回": ["Week 1: Unit 10, Emotions and Personality", ""], "第2回": ["Week 2: Unit 10, Emotions and Personality", "Extensive Reading - 60 minutes<BR/>Writing Journal - 60 minutes"], "第3回": ["Week 3: Unit 10, Emotions and Personality<BR/>Essay 1: The Five-Paragraph Essay", "Extensive Reading  - 60 minutes<BR/>Essay Writing - 3 hours"], "第4回": ["Week 4: Unit 8, Traditional and Modern Medicine", "Extensive Reading - 60 minutes<BR/>Writing Journal - 60 minutes"], "第5回": ["Week 5: Unit 8, Traditional and Modern Medicine<BR/>Debate 1: Traditional vs. Modern Medicine", "Extensive Reading - 60 minutes<BR/>Writing Journal - 60 minutes"], "第6回": ["Week 6: Unit 9, Uncovering the Past", "Extensive Reading  - 60 minutes<BR/>Prepare for Presentation - 2 hours"], "第7回": ["Week 7: Unit 9, Uncovering the Past<BR/>Presentation 1: My Favorite Bit of History", "Extensive Reading - 60 minutes<BR/>Writing Journal - 60 minutes"], "第8回": ["Week 8: Unit 7, Inspired to Protect<BR/>Debate 2: The Economy vs. The Environment", "Extensive Reading  - 60 minutes<BR/>Writing Journal - 60 minutes"], "第9回": ["Week 9: Unit 7, Inspired to Protect<BR/>Essay 2: Persuasive Essay", "Extensive Reading - 60 minutes<BR/>Essay Writing - 3 hours"], "第10回": ["Week 10: Unit 7, Inspired to Protect<BR/>Presentation 2: Protecting the Environment", "Extensive Reading - 60 minutes<BR/>Prepare for Presentation - 2 hours"], "第11回": ["Week 11: Unit 6, Design with Purpose", "Extensive Reading  - 60 minutes<BR/>Writing Journal - 60 minutes"], "第12回": ["Week 12: Unit 6, Design with Purpose<BR/>Essay 3: Research Paper", "Extensive Reading - 60 minutes<BR/>Essay Writing - 4 hours"], "第13回": ["Week 13: Unit 6, Design with Purpose<BR/>Debate 3: Accessible Design", "Extensive Reading - 60 minutes<BR/>Writing Journal - 60 minutes"], "第14回": ["Week 14: Final Presentations", "Prepare for presentation - 3 hours"]}, "評価": {"教科書/Required texts0": ["著者名\nAuthor", "タイトル\nTitle", "発行所\nPublisher", "出版年\nYear of Publication", "ISBN", "ボタン\nButton"], "教科書/Required texts1": ["Becky Tarver Chase & Christien Lee", "Pathways Listening, Speaking, and Critical Thinking 3B, Second Edition", "National Geographic Learning", "2018 年", "978-1-33-756260-7", ""], "教科書/Required texts2": ["", "X-Reading (6-month subscription)", "", "", "9784865390698", ""], "成績評価Grading0": ["種別　Type備考　Note", "割合　Percentage", "評価基準等　Grading Criteria etc."], "成績評価Grading1": ["その他／Others (99)", "100 %", "Tests & Quizzes: 20% Participation: 30% Projects and Presentations: 20% Essays and Homework: 30%"], "更新日時/Date of Update0": "2021年04月28日 18時52分59秒", "項番No.0": [], "項番No.1": ["2021年度", "春学期／Spring", "月曜２時限／Monday 2", "春学期／Spring", "４別－２０５"], "項番No.2": ["2021年度", "春学期／Spring", "水曜４時限／Wednesday 4", "春学期／Spring", "Ｄ－１０４"], "項番No.3": ["2021年度", "春学期／Spring", "金曜２時限／Friday 2", "春学期／Spring", "Ｇ－２２５"]}, "開講キャンパス": "西宮上ケ原キャンパス／Nishinomiya Uegahara Campus", "【科目ナンバー/Course Number】授業名称": "【200】インテンシブ・イングリッシュ　３８／Intensive English", "管理部署": "言語教育研究センター／Language Center", "単位数": "3", "担当者": "エバリー　リディア（EBERLY LYDIA） ", "履修基準年度": "１年", "時限1": "月曜２時限／Monday 2", "時限2": "水曜４時限／Wednesday 4", "時限3": "金曜２時限／Friday 2", "開講期": "春学期／Spring"}