{"履修期": "秋学期集中", "主な教授言語": "日本語", "授業目的": "本講義の目的は受講生がプロジェクト・マネジメント手法を学習することである。プロジェクト・マネジメント手法とは、現状における問題を特定し、問題の原因を分析し、解決策を探り、その実行計画をプロジェクトとして形成するという、問題解決型の戦略的なアプローチの手法である。この手法はプロジェクト・サイクル・マネージメント（PCM）と呼ばれ、国際協力の分野で広く用いられているものであるが、国内の社会開発事業や、個人のプロジェクト等、使用範囲は広い。", "到達目標": "到達目標１．PCMの理論を理解する<br />到達目標２．現状における問題を特定し、問題の原因を分析し、解決策を探ることを通して、実際のプロジェクトがどのように運営されているのかを学ぶ<br />到達目標３．PCM手法を用いて、グループワークでプロジェクトを計画する", "特記事項": "", "関連科目": "", "授業の概要・背景": "", "授業方法": "対面授業。講義と演習（グループワーク）をセットで行う。", "トピック": {"第1回": ["イントロダクション<br />プロジェクト事例紹介", ""], "第2回": ["PCM手法の概要説明", ""], "第3回": ["関係者分析（理論・演習）", ""], "第4回": ["問題分析（理論）", ""], "第5回": ["問題分析（演習）その１", ""], "第6回": ["問題分析（演習）その２", ""], "第7回": ["目的分析（理論）", ""], "第8回": ["目的分析（演習）", ""], "第9回": ["プロジェクトの選択（理論・演習）", ""], "第10回": ["ＰＤＭ<br />プロジェクトの要約（理論・演習）", ""], "第11回": ["ＰＤＭ<br />外部条件（理論・演習）", ""], "第12回": ["ＰＤＭ<br />指標と指標入手手段（理論・演習）", ""], "第13回": ["ＰＤＭ<br />投入／前提条件（理論・演習）", ""], "第14回": ["活動計画表（理論）<br />テスト", ""], "授業外学習2": "「国連ユースボランティア」、「国際社会貢献活動」などのプログラムに興味のある学生には特に受講を勧める。<br />事前配布資料を読み、簡単な課題をやってくる。<br />受講人数制限あり（申込科目：24人）。"}, "評価": {"1": ["", ""], "2": ["", ""], "3": ["", ""], "4": ["", ""], "5": ["", ""], "6": ["", ""], "7": ["", ""], "8": ["", ""], "9": ["", ""], "10": ["", ""], "11": ["", ""], "12": ["", ""], "13": ["", ""], "14": ["", ""], "0": ["", "", "", "", "", ""], "成績評価Grading0": ["種別　Type備考　Note", "割合　Percentage", "評価基準等　Grading Criteria etc."], "成績評価Grading1": ["授業中試験／In-class examination (03)", "80 %", ""], "成績評価Grading2": ["その他／Others (99)", "20 %", "授業参加状況（理解度、ワークショップ貢献度、学習意欲など）"], "項番No.0": [], "項番No.1": ["2024年度", "秋学期集中／Intensive (Fall)", "集中・その他／Concentration/Other", "秋学期集中／Intensive (Fall)", "Ｇ－２２６"]}, "campas": 0, "name": "【200】プロジェクトマネジメントI　３／Project Management I", "管理部署": 24, "単位数": 2, "担当者": "大迫　正弘（OSEKO MASAHIRO） ", "履修基準年度": "１年", "履修登録方法": "申込制", "緊急授業形態": 0, "時限1": 49, "評価1": 2, "評価2": 6, "開講期": 9, "成績評価備考": "割合　Percentage"}