{"履修期": "通年集中", "主な教授言語": "日本語", "授業目的": "心理的支援を要する者等に対して支援を実践しながら，実習指導者又は実習担当教員による指導を受ける。", "到達目標": "心理に関する支援を要する者等に関する知識及び技能の修得", "授業方法": "実習施設にて実習", "トピック": {"授業計画1": "(ア) 心理に関する支援を要する者等に関する以下の知識及び技能の修得<BR/>（１）コミュニケーション，（２）心理検査，（３）心理面接，（４）地域支援等<BR/>(イ) 心理に関する支援を要する者等の理解とニーズの把握及び支援計画の作成<BR/>(ウ) 心理に関する支援を要する者へのチームアプローチ<BR/>(エ) 多職種連携及び地域連携<BR/>(オ) 公認心理師としての職業倫理及び法的義務への理解", "授業外学習2": "実習に必要となる基礎知識を身についておくことが必要である。<BR/>また、接遇等についても各自が学び身につけておくこと。<BR/>授業時間外にもかなりの自己学習時間が必要であることを心しておいて欲しい。"}, "評価": {"成績評価Grading0": ["種別　Type備考　Note", "割合　Percentage", "評価基準等　Grading Criteria etc."], "成績評価Grading1": ["平常リポート／Individual reports (04)", "100 %", ""], "備考Note0": "本科目は、公認心理師法施行規則に定める科目のうち、以下に該当する。\n「10. 心理実践実習」\n(1)実習生が、大学段階での実習を通じて得た公認心理師に必要な知識・技能の基礎的な理解の上に、次の（ア）から（オ）までに掲げる事項について、見学だけでなく、心理に関する支援を要する者等に対して支援を実践しながら、実習指導者又は実習担当教員による指導を受ける。実習施設の分野については主要５分野に関する学外施設（具体的な施設については「公認心理師法施行規則第三条第三項の規定に基づき文部科学大臣及び厚生労働大臣が別に定める施設」（平成29年文部科学省・厚生労働省告示第５号）のとおり。）のうち、３分野以上の施設において実習を受ける。ただし、医療機関は必須とする。また、医療機関以外の施設においては、見学を中心とする実習も含む。\n(ア)心理に関する支援を要する者等に関する以下の知識及び技能の修得\n（１）コミュニケーション\n（２）心理検査\n（３）心理面接\n（４）地域支援等\n(イ)心理に関する支援を要する者等の理解とニーズの把握及び支援計画の作成\n(ウ)心理に関する支援を要する者へのチームアプローチ\n(エ)多職種連携及び地域連携\n(オ)公認心理師としての職業倫理及び法的義務への理解\n(2)担当ケースに関する実習の時間は，他の実習も含め，総計で270時間以上（うち、学外施設での当該実習総時間は90時間以上）とする。\n(3)実習担当教員が、実習生の実習状況について把握し、(1)の（ア）から（オ）までに掲げる事項について基本的な水準の修得ができるように、実習生及び実習指導者との連絡調整を密に行う。\n(4)大学又は大学院に設置されている心理職を養成するための相談室での実習は主要５分野のいずれにも含まれないこととして取り扱う。", "更新日時/Date of Update1": "2021年10月12日 15時44分08秒", "項番No.0": [], "項番No.1": ["2021年度", "通年集中／Intensive (Year Round)", "集中・その他／Concentration/Other", "通年集中／Intensive (Year Round)", "未定"]}, "campas": 0, "name": "【500】心理科学実践Ｋ（心理実践実習）　３／Adv Pra in Psy Sci K (Practicum in Psychology)", "管理部署": 30, "単位数": 2, "担当者": "佐藤　寛（SATO HIROSHI） ", "履修基準年度": "１年", "授業形態": 0, "緊急授業形態": 0, "オンライン授業形態": 0, "時限1": 49, "評価1": 3, "開講期": 7}