{"履修期": "秋学期", "主な教授言語": "日本語", "授業目的": "<div>海外の経済史研究の動向をさまざまな観点から学び，受講者が現代のさまざまな経済現象に<span style=\"font-size:13.28px;\">ついて歴史から問題を発見し，考察する。</span></div>", "到達目標": "今日の世界の経済的課題を歴史的観点から理解できるようになる。", "特記事項": "", "関連科目": "", "授業の概要・背景": "", "授業方法": "初回のガイダンスは教員による講義，以降は学生の発表と議論による演習形式。", "トピック": {"第1回": ["<div>ガイダンス。</div><div>必ず第1回のガイダンスに出席すること。 シラバスを「最後まで」読んだ上で，本講義の内容と授業方針に納得した者は，履修登録し，授業に臨むこと。</div>", "授業の復習。"], "第2回": ["学生による報告と議論。", "<span style=\"font-size:13.28px;\">授業の復習。</span>"], "第3回": ["<span style=\"font-size:13.28px;\">学生による報告と議論。</span>", "<span style=\"font-size:13.28px;\">授業の復習。</span>"], "第4回": ["<span style=\"font-size:13.28px;\">学生による報告と議論。</span>", "<span style=\"font-size:13.28px;\">授業の復習。</span>"], "第5回": ["<span style=\"font-size:13.28px;\">学生による報告と議論。</span>", "<span style=\"font-size:13.28px;\">授業の復習。</span>"], "第6回": ["<span style=\"font-size:13.28px;\">学生による報告と議論。</span>", "<span style=\"font-size:13.28px;\">授業の復習。</span>"], "第7回": ["<span style=\"font-size:13.28px;\">学生による報告と議論。</span>", "<span style=\"font-size:13.28px;\">授業の復習。</span>"], "第8回": ["<span style=\"font-size:13.28px;\">学生による報告と議論。</span>", "<span style=\"font-size:13.28px;\">授業の復習。</span>"], "第9回": ["<span style=\"font-size:13.28px;\">学生による報告と議論。</span>", "<span style=\"font-size:13.28px;\">授業の復習。</span>"], "第10回": ["<span style=\"font-size:13.28px;\">学生による報告と議論。</span>", "<span style=\"font-size:13.28px;\">授業の復習。</span>"], "第11回": ["<span style=\"font-size:13.28px;\">学生による報告と議論。</span>", "<span style=\"font-size:13.28px;\">授業の復習。</span>"], "第12回": ["<span style=\"font-size:13.28px;\">学生による報告と議論。</span>", "<span style=\"font-size:13.28px;\">授業の復習。</span>"], "第13回": ["<span style=\"font-size:13.28px;\">学生による報告と議論。</span>", "<span style=\"font-size:13.28px;\">授業の復習。</span>"], "第14回": ["<span style=\"font-size:13.28px;\">学生による報告と議論。</span>", "<span style=\"font-size:13.28px;\">授業の復習。</span>"], "授業計画1": "<div>報告内容のレベルが低い場合はやり直しをさせる。報告担当以外の者も積極的に議論するこ<span style=\"font-size:13.28px;\">と。</span></div>", "授業外学習2": "指定された論文を徹底的に読込み，一言一句にいたるまで完全に理解すること。疑問点・分からない点を明確にすること。"}, "評価": {"1": ["", ""], "2": ["", ""], "3": ["", ""], "4": ["", ""], "5": ["", ""], "6": ["", ""], "7": ["", ""], "8": ["", ""], "9": ["", ""], "10": ["", ""], "11": ["", ""], "12": ["", ""], "13": ["", ""], "14": ["", ""], "0": ["", "", "", "", "", ""], "成績評価Grading0": ["種別　Type備考　Note", "割合　Percentage", "評価基準等　Grading Criteria etc."], "成績評価Grading1": ["平常リポート／Individual reports (04)", "60 %", ""], "成績評価Grading2": ["その他／Others (99)", "40 %", "平常点（出席状況，議論への参加度，授業への貢献など）。下記の備考を良く読 むこと。"], "項番No.0": [], "項番No.1": ["2024年度", "秋学期／Fall", "月曜２時限／Monday 2", "秋学期／Fall", "院１－２０８"]}, "campas": 0, "name": "【600】経済史Ｂ／Economic History B", "管理部署": 33, "単位数": 2, "担当者": "高島　正憲（TAKASHIMA MASANORI） ", "履修基準年度": "１年", "履修登録方法": "本登録", "緊急授業形態": 0, "時限1": 1, "評価1": 3, "評価2": 6, "開講期": 2}