{"履修期": "春学期", "主な教授言語": "日本語", "授業目的": "学部で学んだ量子力学の基礎を発展学習し、量子情報理論に触れる。", "到達目標": "量子情報理論の基礎を学ぶ。", "特記事項": "", "関連科目": "", "授業の概要・背景": "", "授業方法": "対面講義形式", "トピック": {"第1回": ["【スタートアップウィーク】リンク：https://kwansei.jp.panopto.com/Panopto/Pages/Viewer.aspx?id=84bf7853-b9c2-4c9d-82d6-b4170097063d<br />オンライン授業（オンデマンド型）／《15分》<br />ガイダンス（成績評価の基準と課題提出について）", "学部で学んだ量子力学を復習しておく"], "第2回": ["【コアウィークス①】<br />対面授業／《90分》<br /><span style=\"font-size:13.28px;\">量子力学の公理と基礎１（復習）</span>", "課題に取り組むこと"], "第3回": ["<span style=\"font-size:13.28px;\">【コアウィークス②】</span><br /><span style=\"font-size:13.28px;\">対面授業／《90分》</span><br /><span style=\"font-size:13.28px;\">量子力学の公理</span><span style=\"font-size:13.28px;\">と基礎</span><span style=\"font-size:13.28px;\">２</span><span style=\"font-size:13.28px;\">（復習）</span>", "<span style=\"font-size:13.28px;\">課題に取り組むこと</span>"], "第4回": ["<span style=\"font-size:13.28px;\">【フレックスアワーズ①】</span><br /><span style=\"font-size:13.28px;\">オンライン授業（オンデマンド型）／《75分》</span><br /><span style=\"font-size:13.28px;\">コアウィークス①②</span><span style=\"font-size:13.28px;\">の演習問題解説</span>", "<span style=\"font-size:13.28px;\">理解できていない箇所を把握し、復習すること</span>"], "第5回": ["<span style=\"font-size:13.28px;\">【コアウィークス③】</span><br /><span style=\"font-size:13.28px;\">対面授業／《90分》</span><br /><span style=\"font-size:13.28px;\">シュテルン・ゲルラッハの実験とスピン角運動量</span>", "<span style=\"font-size:13.28px;\">課題に取り組むこと</span>"], "第6回": ["<span style=\"font-size:13.28px;\"><span style=\"font-size:13.28px;\">【</span>フレックスアワーズ②】</span><br /><span style=\"font-size:13.28px;\">オンライン授業（オンデマンド型）／《45分》</span><br /><span style=\"font-size:13.28px;\">コアウィークス③</span><span style=\"font-size:13.28px;\">の演習問題解説</span>", "<span style=\"font-size:13.28px;\">理解できていない箇所を把握し、復習すること</span>"], "第7回": ["<span style=\"font-size:13.28px;\">【コアウィークス④】</span><br /><span style=\"font-size:13.28px;\">対面授業／《90分》</span><br /><span style=\"font-size:13.28px;\">純粋状態と混合状態</span>", "<span style=\"font-size:13.28px;\">課題に取り組むこと</span>"], "第8回": ["<span style=\"font-size:13.28px;\">【コアウィークス⑤】</span><div><span style=\"font-size:13.28px;\">対面授業／《90分》</span><br /><div style=\"font-size:13.28px;\"><span style=\"font-size:13.28px;\">EPRパラドックスとベルの不等式</span></div></div>", "<span style=\"font-size:13.28px;\">課題に取り組むこと</span>"], "第9回": ["<span style=\"font-size:13.28px;\">【フレックスアワーズ③】</span><br /><span style=\"font-size:13.28px;\">オンライン授業（オンデマンド型）／《45分》</span><div><span style=\"font-size:13.28px;\">コアウィークス④⑤の演習問題解説</span></div>", "<span style=\"font-size:13.28px;\">課題に取り組むこと</span>"], "第10回": ["<span style=\"font-size:13.28px;\">【コアウィークス⑥】</span><br /><span style=\"font-size:13.28px;\">対面授業／《90分》</span><br /><span style=\"font-size:13.28px;\">古典情報理論１</span>", "<span style=\"font-size:13.28px;\">課題に取り組むこと</span>"], "第11回": ["<div style=\"font-size:13.28px;\"><span style=\"font-size:13.28px;\">【コアウィークス⑦】</span><br /><span style=\"font-size:13.28px;\">対面授業／《90分》</span><br /><div style=\"font-size:13.28px;\"><span style=\"font-size:13.28px;\">古典情報理論２</span></div></div>", "<span style=\"font-size:13.28px;\">理解できていない箇所を把握し、復習すること</span>"], "第12回": ["<div style=\"font-size:13.28px;\"><div style=\"font-size:13.28px;\"><span style=\"font-size:13.28px;\">【コアウィークス⑧】</span><br /><span style=\"font-size:13.28px;\">対面授業／《90分》</span><br /></div><div style=\"font-size:13.28px;\"><span style=\"font-size:13.28px;\">量子情報エントロピー１</span></div></div>", "<span style=\"font-size:13.28px;\">課題に取り組むこと</span>"], "第13回": ["<div style=\"font-size:13.28px;\"><span style=\"font-size:13.28px;\">【コアウィークス⑨</span><span style=\"font-size:13.28px;\">】</span></div><div style=\"font-size:13.28px;\"><span style=\"font-size:13.28px;\">対面授業／《90分》</span><br /><div style=\"font-size:13.28px;\"><span style=\"font-size:13.28px;\">量子情報エントロピー２</span></div></div>", "<span style=\"font-size:13.28px;\">課題に取り組むこと</span>"], "第14回": ["<div style=\"font-size:13.28px;\"><span style=\"font-size:13.28px;\">【フレックスアワーズ④】</span></div><div style=\"font-size:13.28px;\"><span style=\"font-size:13.28px;\">オンライン授業（オンデマンド型）／《45分》</span></div><div style=\"font-size:13.28px;\"><span style=\"font-size:13.28px;\">コアウィークス⑥〜⑨の演習問題解説</span></div>", "<span style=\"font-size:13.28px;\">理解できていない箇所を把握し、復習すること</span>"], "第15回": ["<span style=\"font-size:13.28px;\">【コアウィークス⑩】</span><br /><span style=\"font-size:13.28px;\">対面授業／《90分》</span><div style=\"font-size:13.28px;\"><span style=\"font-size:13.28px;\">量子テレポーテーション</span></div>", "<span style=\"font-size:13.28px;\">課題に取り組むこと</span>"], "第16回": ["<span style=\"font-size:13.28px;\">【コアウィークス⑪】</span><br /><span style=\"font-size:13.28px;\">対面授業／《90分》</span><br /><span style=\"font-size:13.28px;\">量子エンタングルメント１</span>", "<span style=\"font-size:13.28px;\">課題に取り組むこと</span>"], "第17回": ["<span style=\"font-size:13.28px;\">【コアウィークス⑫】</span><br /><span style=\"font-size:13.28px;\">対面授業／《90分》</span><br /><span style=\"font-size:13.28px;\">量子エンタングルメント２</span>", "<span style=\"font-size:13.28px;\">課題に取り組むこと</span>"], "第18回": ["<div style=\"font-size:13.28px;\"><span style=\"font-size:13.28px;\">【フレックスアワーズ⑤】</span></div><div style=\"font-size:13.28px;\"><span style=\"font-size:13.28px;\">オンライン授業（オンデマンド型）／《45分》</span></div><div style=\"font-size:13.28px;\"><span style=\"font-size:13.28px;\">コアウィークス</span><span style=\"font-size:13.28px;\">⑩</span><span style=\"font-size:13.28px;\">〜</span><span style=\"font-size:13.28px;\">⑫</span><span style=\"font-size:13.28px;\">の演習問題解説</span></div>", "<span style=\"font-size:13.28px;\">理解できていない箇所を把握し、復習すること</span>"]}, "評価": {"参考書/Reference books0": ["著者名\nAuthor", "タイトル\nTitle", "発行所\nPublisher", "出版年\nYear of Publication", "ISBN", "ボタン\nButton"], "参考書/Reference books1": ["近藤 慶一", "量子力学講義I: 物理の一般原理と数学的定式化", "共立出版", "2023 年", "978-4-3200-3625-3", ""], "参考書/Reference books2": ["近藤 慶一", "量子力学講義II: 原子から量子もつれまで", "共立出版", "2023 年", "978-4-3200-3626-0", ""], "参考書/Reference books3": ["細谷 曉夫", "量子と情報（量子力学選書）", "裳華房", "2025 年", "", ""], "参考書/Reference books4": ["中田 芳史", "量子情報理論: 情報から物理現象の理解まで", "朝倉書店", "2024 年", "978-4-2541-3532-9", ""], "成績評価Grading0": ["種別　Type備考　Note", "割合　Percentage", "評価基準等　Grading Criteria etc."], "成績評価Grading1": ["定期試験に代わるリポート／Term paper to replace the final examination (02)", "50 %", ""], "成績評価Grading2": ["平常リポート／Individual reports (04)", "50 %", ""], "更新日時/Date of Update0": ["2026年03月24日 18時12分31秒"], "項番No.0": [], "項番No.1": ["2026年度", "春学期／Spring", "木曜４時限／Thursday 4", "春学期／Spring", "ＩＶ－２１２"]}, "campas": 1, "name": "【511】量子力学特論I／Advanced Quantum Mechanics I", "管理部署": 35, "単位数": 2, "担当者": "山田　雅俊（YAMADA MASATOSHI） ", "履修基準年度": "１年", "履修登録方法": "本登録", "開講期": 1, "時限1": 24, "時限1_term": 0, "評価1": 1, "評価2": 3}