{"履修期": "春学期", "主な教授言語": "日本語", "授業目的": "フランス・オペラがいかに時の政治権力と密接な関係で結ばれていたかを理解する。その目的のために必要な基礎的な知識・観点を学ぶ。", "到達目標": "１７世紀後半から１９世後半にかけてのフランス・オペラの表現と政治権力との結びつきを認識してオペラと権力関係が分析できること。", "授業方法": "対面授業(一部同時双方向型オンライン授業を含む)を原則とする。新型コロナウイルス感染症の蔓延状況によっては、Zoomを利用した同時双方向型オンライン授業に全面的に切り替える。関連資料の講読、映像・聴覚資料を用いながらの講義とともに、受講生の発表・討論によって授業を進める。", "トピック": {"第1回": ["4/13 : 本講義のためのオリエンテーション。音楽と政治の関係についての考察。", ""], "第2回": ["4/20 : ルイ１４世の治世とリュリの「叙情悲劇」の政治性　1", ""], "第3回": ["4/27 : ルイ１４世の治世とリュリの「叙情悲劇」の政治性　2", ""], "第4回": ["5/11 : オペラ・コミックの隆盛と政治", ""], "第5回": ["5/18 : フランス革命とオペラ・コミック 1", ""], "第6回": ["5/25 ：フランス革命とオペラ・コミック 2", ""], "第7回": ["6/1 : フランス革命とグレトリー 1", ""], "第8回": ["6/8 : フランス革命とグレトリー 2", ""], "第9回": ["6/15 : 共和主義の精神とオペラ", ""], "第10回": ["6/22 : ブルジョワ市民社会とオペラ：ナポレオンとスポンティーニ  1", ""], "第11回": ["6/29 : ブルジョワ市民社会とオペラ：ナポレオンとスポンティーニ　 2", ""], "第12回": ["7/6 : ブルジョワ市民社会とグランド・オペラ　マイヤベーア 1", ""], "第13回": ["7/13 : ブルジョワ市民社会とグランド・オペラ　マイヤベーア　2", ""], "第14回": ["7/20 : 総括：「社会・文化装置」としてのオペラとその政治性", ""], "授業外学習2": "フランス語の文献を原文で理解できるだけのフランス語の読解力を求める。また、ヨーロッパ音楽に関して知識と関心があること。"}, "評価": {"教科書/Required texts0": ["著者名\nAuthor", "タイトル\nTitle", "発行所\nPublisher", "出版年\nYear of Publication", "ISBN", "ボタン\nButton"], "教科書/Required texts1": ["D.Astor /G. Courchelle /P. Taieb", "Opera-ci Opera-la", "Gallimard", "2009 年", "978-2-07-039657-3", ""], "教科書/Required texts2": ["Textes réunis par J. Duron", "Grétry en société", "Mardaga", "2009 年", "978-2-8047-0036-2", ""], "教科書Required texts0": "必要部分はコピーして配布する。", "参考文献・資料Reference books0": "Apostolidès (Jean-Marie), Le prince sacré, Editions du Minuit, 1985.\nMongrédien, (Jean), La musique en France des Lumières au Romantisme 1789-1830, Flammarion, 1986.\nMusique, filiations et ruptures, Cité de la musique, 2005.", "学生による授業評価の方法Course Evaluation by Students0": "最終授業中に研究科所定様式で実施", "成績評価Grading0": ["種別　Type備考　Note", "割合　Percentage", "評価基準等　Grading Criteria etc."], "成績評価Grading1": ["平常リポート／Individual reports (04)", "50 %", "レポート"], "成績評価Grading2": ["その他／Others (99)", "50 %", "授業への参加度（議論・発言・質問等），個人発表を総合的に評価する。"], "更新日時/Date of Update0": "2021年01月15日 17時17分25秒", "項番No.0": [], "項番No.1": ["2021年度", "春学期／Spring", "火曜２時限／Tuesday 2", "春学期／Spring", "未定"]}, "開講キャンパス": "西宮上ケ原キャンパス／Nishinomiya Uegahara Campus", "【科目ナンバー/Course Number】授業名称": "【550】フランス語圏文化Ｂ／Culture in French-Speaking Regions B", "管理部署": "言語コミュニケーション前期／Graduate School of Language, Communication, and Culture Master's Course", "単位数": "2", "担当者": "藤田　友尚（FUJITA TOMONAO） ", "履修基準年度": "１年", "時限1": "火曜２時限／Tuesday 2", "開講期": "春学期／Spring"}